README.txt
setup.py
h5pom/__init__.py
h5pom/core.py
h5pom/descriptors.py
h5pom.egg-info/PKG-INFO
h5pom.egg-info/SOURCES.txt
h5pom.egg-info/dependency_links.txt
h5pom.egg-info/requires.txt
h5pom.egg-info/top_level.txt