Metadata-Version: 1.1
Name: h5pom
Version: 0.1
Summary: An ORM for hdf5 using h5py for basic IO
Home-page: https://bitbucket.org/jbmohler/h5pom
Author: Joel B. Mohler
Author-email: joel@kiwistrawberry.us
License: BSD
Platform: UNKNOWN
Classifier: Development Status :: 3 - Alpha
Classifier: Intended Audience :: Developers
Classifier: License :: OSI Approved :: BSD License
Classifier: Programming Language :: Python :: 2
Classifier: Topic :: Database :: Front-Ends
Classifier: Operating System :: OS Independent
